letsmaintain/__init__.py
letsmaintain/apps.py
letsmaintain/middleware.py
letsmaintain/tests/__init__.py
letsmaintain/tests/test_middleware.py
django_letsmaintain-1.0.9.dist-info/METADATA
django_letsmaintain-1.0.9.dist-info/WHEEL
django_letsmaintain-1.0.9.dist-info/licenses/LICENSE
django_letsmaintain-1.0.9.dist-info/RECORD
